pyreporting/__init__.py
pyreporting/logger.py
pyreporting/progress.py
pyreporting/progress_bar.py
pyreporting/progress_bar_pyside.py
pyreporting/reporting.py
pyreporting/util.py
pyreporting-0.0.6.dist-info/METADATA
pyreporting-0.0.6.dist-info/WHEEL
pyreporting-0.0.6.dist-info/licenses/LICENSE
pyreporting-0.0.6.dist-info/RECORD
